<commands
	xmlns:xsi="http://www.w3.org/2001/XMLSchema-instance"
	xsi:noNamespaceSchemaLocation="part2in.xsd"
	spatialWidth="1024"
	spatialHeight="1024"
	remoteSpatialWidth="1024"
	remoteSpatialHeight="1024"
	g="3"
	pmOrder="1">
	
	 <createCity name="Baltimore" localX="140" localY="37" remoteX="140" remoteY="37" radius="0" color="black"/>
	 <createCity name="Chicago" localX="133" localY="34" remoteX="28" remoteY="111" radius="0" color="black"/>
	 <createCity name="New_York" localX="200" localY="300" remoteX="600" remoteY="600" radius="0" color="black"/>
	 <createCity name="Toronto" localX="100" localY="400" remoteX="300" remoteY="500" radius="0" color="black"/>
	 <createCity name="Zurich" localX="1000" localY="1000" remoteX="140" remoteY="37" radius="0" color="black"/>
	 <createCity name="Paris" localX="500" localY="400" remoteX="140" remoteY="37" radius="0" color="black"/>
	 <createCity name="Amsterdam" localX="450" localY="450" remoteX="300" remoteY="500" radius="0" color="black"/>
	 <createCity name="Auckland" localX="2000" localY="2" remoteX="140" remoteY="37" radius="0" color="black"/>
	 <createCity name="Tokyo" localX="1700" localY="1000" remoteX="600" remoteY="600" radius="0" color="black"/>
	 <createCity name="Cairo" localX="1000" localY="200" remoteX="28" remoteY="111" radius="0" color="black"/>
	 <createCity name="Vancouver" localX="0" localY="1025" remoteX="600" remoteY="600" radius="0" color="black"/>


	 <mapRoad start="Sydney" end="Auckland"/>
	 <mapRoad start="Auckland" end="Sydney"/>
	 <mapRoad start="Auckland" end="Auckland"/>
	 <mapRoad start="Cairo" end="Chicago"/>
	 <mapRoad start="Chicago" end="Cairo"/>
	 <mapRoad start="Chicago" end="New_York"/>
	 <mapRoad start="Chicago" end="New_York"/>
	 <mapRoad start="New_York" end="Chicago"/>
	 <mapRoad start="Tokyo" end="Auckland"/> 
	 <mapRoad start="Baltimore" end="Chicago"/>
	 <mapRoad start="New_York" end="Zurich"/>
	 <mapRoad start="Zurich" end="Paris"/>
	 <mapRoad start="Paris" end="Amsterdam"/>
	 <mapRoad start="Tokyo" end="Paris"/>
	 <mapRoad start="Tokyo" end="Vancouver"/>


	 <mapAirport name="Cairo" localX="1000" localY="200" remoteX="28" remoteY="111" terminalName="OJ" terminalX="28" terminalY="111" terminalCity="Chicago"/>


	 
	 <saveMap name="part2.public.ACTfile12"/>

	 <printPMQuadtree />

	 <nearestCity localX="0" localY="0" remoteX="600" remoteY="600" />
	 <nearestCity localX="1024" localY="1024" rremoteX="140" remoteY="37" />
	 <nearestCity localX="475" localY="425" remoteX="140" remoteY="37" />
	 <nearestCity localX="1700" localY="1000" remoteX="600" remoteY="600" />
	 <nearestCity localX="1000" localY="200" remoteX="300" remoteY="500"  />
	 <nearestCity localX="450" localY="450" remoteX="28" remoteY="111" />
 
</commands>
