<?xml version="1.0" encoding="UTF-8" standalone="no"?>
<results>
  <success>
    <command name="createCity"/>
    <parameters>
      <name value="Riverrun"/>
      <x value="45"/>
      <y value="75"/>
      <radius value="5"/>
      <color value="black"/>
    </parameters>
    <output/>
  </success>
  <success>
    <command name="createCity"/>
    <parameters>
      <name value="Braavos"/>
      <x value="150"/>
      <y value="90"/>
      <radius value="5"/>
      <color value="black"/>
    </parameters>
    <output/>
  </success>
  <success>
    <command name="createCity"/>
    <parameters>
      <name value="Pentos"/>
      <x value="165"/>
      <y value="75"/>
      <radius value="5"/>
      <color value="blue"/>
    </parameters>
    <output/>
  </success>
  <success>
    <command name="createCity"/>
    <parameters>
      <name value="Winterfell"/>
      <x value="50"/>
      <y value="110"/>
      <radius value="5"/>
      <color value="black"/>
    </parameters>
    <output/>
  </success>
  <success>
    <command name="createCity"/>
    <parameters>
      <name value="Kings_Landing"/>
      <x value="60"/>
      <y value="60"/>
      <radius value="5"/>
      <color value="black"/>
    </parameters>
    <output/>
  </success>
  <error type="startPointDoesNotExist">
    <command name="mapRoad"/>
    <parameters>
      <start value="Fartsburgh"/>
      <end value="UrMumsHouse"/>
    </parameters>
  </error>
  <error type="endPointDoesNotExist">
    <command name="mapRoad"/>
    <parameters>
      <start value="Riverrun"/>
      <end value="Blork"/>
    </parameters>
  </error>
  <success>
    <command name="mapRoad"/>
    <parameters>
      <start value="Winterfell"/>
      <end value="Kings_Landing"/>
    </parameters>
    <output>
      <roadCreated end="Kings_Landing" start="Winterfell"/>
    </output>
  </success>
</results>